{
    "whole_procedure": true,
    "do_nothing": false,
    "run_bootstrap": false,
    "clean": false,
    "install": true,
    "build_debug": [
        true,
        false
    ],
    "build_static": [
        true,
        false
    ],
    "link_static": [
        false
    ],
    "threading": [
        "multi"
    ],
    "address_model": [
        "64"
    ],
    "components": [
        "atomic",
        "chrono",
        "container",
        "context",
        "contract",
        "coroutine",
        "date_time",
        "exception",
        "fiber",
        "filesystem",
        "graph",
        "graph_parallel",
        "headers",
        "iostreams",
        "json",
        "locale",
        "log",
        "math",
        "mpi",
        "nowide",
        "program_options",
        "random",
        "regex",
        "serialization",
        "stacktrace",
        "system",
        "test",
        "thread",
        "timer",
        "type_erasure",
        "wave"
    ],
    "architecture": "x86",
    "toolset": "msvc-14.2",
    "repo": "https://github.com/boostorg/boost.git",
    "tag": "boost-1.80.0",
    "version": "1.80.0",
    "install_dir_name": "boost-1.80.0"
}